{
  "gitSyncId": "69d3a680df758d40c23d95b3_8aed5895-81d5-4b4f-b2ac-e7d48235b79b",
  "id": "Menu_ValidarSesion",
  "pluginId": "restapi-plugin",
  "pluginType": "API",
  "unpublishedAction": {
    "actionConfiguration": {
      "autoGeneratedHeaders": [
        {
          "key": "content-type",
          "value": "application/json"
        }
      ],
      "body": "",
      "bodyFormData": [],
      "encodeParamsToggle": true,
      "formData": {
        "apiContentType": "application/json"
      },
      "headers": [],
      "httpMethod": "POST",
      "httpVersion": "HTTP11",
      "paginationType": "NONE",
      "path": "/ValidarSesion",
      "pluginSpecifiedTemplates": [
        {
          "value": true
        }
      ],
      "queryParameters": [
        {
          "key": "p_sesion_id",
          "value": "{{this.params.p_sesion_id || ''}}"
        }
      ],
      "timeoutInMillisecond": 10000
    },
    "confirmBeforeExecute": false,
    "datasource": {
      "id": "DiamanteDev",
      "isAutoGenerated": false,
      "name": "DiamanteDev",
      "pluginId": "restapi-plugin"
    },
    "dynamicBindingPathList": [
      {
        "key": "queryParameters[0].value"
      }
    ],
    "name": "ValidarSesion",
    "pageId": "Menu",
    "runBehaviour": "MANUAL",
    "userSetOnLoad": false
  }
}