{
  "gitSyncId": "69d3a680df758d40c23d95b3_3626483b-56be-4eee-ac6c-4878e6924c41",
  "id": "Menu_infoPCLAuth.procesarLogin",
  "pluginId": "js-plugin",
  "pluginType": "JS",
  "unpublishedAction": {
    "actionConfiguration": {
      "encodeParamsToggle": true,
      "jsArguments": [
        {
          "name": "data"
        },
        {
          "name": "paginaDestino",
          "value": "MENU"
        }
      ],
      "paginationType": "NONE",
      "timeoutInMillisecond": 10000
    },
    "collectionId": "Menu_infoPCLAuth",
    "confirmBeforeExecute": false,
    "datasource": {
      "isAutoGenerated": false,
      "name": "UNUSED_DATASOURCE",
      "pluginId": "js-plugin"
    },
    "dynamicBindingPathList": [
      {
        "key": "body"
      }
    ],
    "fullyQualifiedName": "infoPCLAuth.procesarLogin",
    "name": "procesarLogin",
    "pageId": "Menu",
    "runBehaviour": "MANUAL",
    "userSetOnLoad": false
  }
}